sparc/__init__.py
sparc/client/__init__.py
sparc/client/_version.py
sparc/client/client.py
sparc/client/zinchelper.py
sparc/client/services/__init__.py
sparc/client/services/_default.py
sparc/client/services/metadata.py
sparc/client/services/o2sparc.py
sparc/client/services/pennsieve.py
sparc_client-0.4.1.dist-info/licenses/LICENSE
sparc_client-0.4.1.dist-info/METADATA
sparc_client-0.4.1.dist-info/WHEEL
sparc_client-0.4.1.dist-info/top_level.txt
sparc_client-0.4.1.dist-info/RECORD
