Metadata-Version: 2.4
Name: sparc.client
Version: 0.4.1
Summary: NIH SPARC Python Client
Author-email: Patryk Orzechowski <patryk@upenn.edu>
Maintainer-email: Patryk Orzechowski <patryk@upenn.edu>
License:                                  Apache License
Project-URL: homepage, https://sparc.science
Project-URL: documentation, https://docs.sparc.science/docs/sparc-python-client
Project-URL: repository, https://github.com/nih-sparc/sparc.client
Project-URL: changelog, https://github.com/nih-sparc/sparc.client/blob/main/CHANGELOG.md
Keywords: data science,datasets
Classifier: Development Status :: 4 - Beta
Classifier: Intended Audience :: Developers
Classifier: Intended Audience :: Information Technology
Classifier: Intended Audience :: Science/Research
Classifier: License :: OSI Approved :: Apache Software License
Classifier: Programming Language :: Python :: 3.10
Classifier: Topic :: Scientific/Engineering
Classifier: Topic :: Scientific/Engineering :: Bio-Informatics
Classifier: Topic :: Scientific/Engineering :: Information Analysis
Classifier: Topic :: Software Development
Classifier: Topic :: Software Development :: Libraries
Classifier: Topic :: Software Development :: Libraries :: Python Modules
Requires-Python: >=3.9
License-File: LICENSE
Requires-Dist: osparc~=0.5.0
Requires-Dist: pennsieve2>=0.1.2
Requires-Dist: cmlibs.zinc>=4.0.0
Requires-Dist: cmlibs.utils>=0.6.0
Requires-Dist: cmlibs.exporter>=0.9.0
Requires-Dist: scaffoldmaker>=0.10.0
Requires-Dist: mbfxml2ex>=0.8.3
Provides-Extra: test
Requires-Dist: pytest~=7.2; extra == "test"
Requires-Dist: pytest-cov; extra == "test"
Requires-Dist: pytest-mock; extra == "test"
Requires-Dist: flake8; extra == "test"
Requires-Dist: black; extra == "test"
Requires-Dist: responses; extra == "test"
Dynamic: license-file
